torchslime/__init__.py
torchslime/callback/__init__.py
torchslime/callback/common.py
torchslime/core/__init__.py
torchslime/core/context.py
torchslime/core/handler.py
torchslime/core/status.py
torchslime/data/__init__.py
torchslime/experiment/__init__.py
torchslime/log/__init__.py
torchslime/log/directory.py
torchslime/metric/__init__.py
torchslime/module/__init__.py
torchslime/module/config.py
torchslime/template/__init__.py
torchslime/template/build.py
torchslime/util/__init__.py
torchslime/util/formatter.py
torchslime/util/table.py
torchslime/util/terminal.py
torchslime/util/type.py
torchslime-0.1.0.dist-info/LICENSE
torchslime-0.1.0.dist-info/METADATA
torchslime-0.1.0.dist-info/WHEEL
torchslime-0.1.0.dist-info/top_level.txt
torchslime-0.1.0.dist-info/RECORD
