Metadata-Version: 2.1
Name: torchslime
Version: 0.1.0
Summary: TorchSlime is a PyTorch-based framework that helps you easily build your DL projects with pre-defined, highly extensible pipelines and other utils.
Home-page: https://github.com/johncaged/TorchSlime
Author: Zikang Liu
Author-email: liuzikang0625@gmail.com
License: MIT License
Platform: UNKNOWN
License-File: LICENSE
